dstkit/__init__.py
dstkit/geohash.py
dstkit-0.0.1.dist-info/LICENSE
dstkit-0.0.1.dist-info/METADATA
dstkit-0.0.1.dist-info/WHEEL
dstkit-0.0.1.dist-info/top_level.txt
dstkit-0.0.1.dist-info/RECORD
