Metadata-Version: 2.1
Name: dstkit
Version: 0.0.1
Summary: Data science toolkit
Home-page: https://github.com/pypa/sampleproject
Author: Daniel J. Lewis
License: UNKNOWN
Platform: UNKNOWN
Classifier: Programming Language :: Python :: 3
Classifier: License :: OSI Approved :: MIT License
Classifier: Operating System :: OS Independent
Classifier: Natural Language :: English
